{"fields":["Open","In Progress","Published"],"tasks":[{"id":"d5da99f3-1207-4daf-85a5-735ac80b6d2b","title":"some task","description":"lalala","publishDate":"Test publish-date","assignee":"asd","currentField":"In Progress"},{"id":"35467ef9-0df4-47a5-b177-12f30cc331dd","title":"some task","description":"lalala","publishDate":"Test","assignee":"asdsaw","currentField":"In Progress"},{"id":"529bcd95-ae1f-4003-a60b-3e200774df3e","title":"some task","description":"lalala","publishDate":"04-06-2021","assignee":"asdsaw","currentField":"open"},{"id":"b6450f88-6773-4891-97cb-ad604d16a2c9","title":"some task","description":"lalala","publishDate":"04-06-2021","assignee":"asdsaw","currentField":"open"},{"id":"52ed52df-cd9b-4955-a0b8-26957b6d8ee8","title":"some task","description":"lalala","publishDate":"Test","assignee":"asdsaw","currentField":"Published"},{"id":"1df81ac5-1ea4-4cf0-958d-7956fa31d609","title":"some task","description":"lalala","publishDate":"Test","assignee":"asdsaw","currentField":"Published"}]}